nitroflare_uploader/__init__.py
nitroflare_uploader/uploader.py
nitroflare_uploader-1.1.0.dist-info/METADATA
nitroflare_uploader-1.1.0.dist-info/WHEEL
nitroflare_uploader-1.1.0.dist-info/top_level.txt
nitroflare_uploader-1.1.0.dist-info/RECORD
